ex2mcmc/__init__.py
ex2mcmc/gan_distribution.py
ex2mcmc/models/__init__.py
ex2mcmc/models/base.py
ex2mcmc/models/mmc.py
ex2mcmc/models/rnvp.py
ex2mcmc/models/rnvp_minimal.py
ex2mcmc/models/utils.py
ex2mcmc/old_samplers.py
ex2mcmc/pyro_samplers.py
ex2mcmc/sample.py
ex2mcmc/samplers.py
ex2mcmc/sampling_utils/__init__.py
ex2mcmc/sampling_utils/adaptive_mc.py
ex2mcmc/sampling_utils/adaptive_sir_loss.py
ex2mcmc/sampling_utils/distributions.py
ex2mcmc/sampling_utils/ebm_sampling.py
ex2mcmc/sampling_utils/linear_regression.py
ex2mcmc/sampling_utils/logistic_regression.py
ex2mcmc/sampling_utils/mcmc_base.py
ex2mcmc/sampling_utils/metrics.py
ex2mcmc/sampling_utils/total_variation.py
ex2mcmc/utils/__init__.py
ex2mcmc/utils/callbacks.py
ex2mcmc/utils/general_utils.py
ex2mcmc/utils/metrics/compute_fid_tf.py
ex2mcmc/utils/metrics/inception_score.py
ex2mcmc-0.0.4.dist-info/LICENSE
ex2mcmc-0.0.4.dist-info/METADATA
ex2mcmc-0.0.4.dist-info/WHEEL
ex2mcmc-0.0.4.dist-info/RECORD
