Metadata-Version: 2.1
Name: ex2mcmc
Version: 0.0.4
Summary: Local-Global MCMC kernels: the bost of both worlds (NeurIPS 2022)
Home-page: http://github.com/svsamsonov/ex2mcmc_new.git
License: MIT
Keywords: mcmc,adaptive mcmc,ex2mcmc,sampling,normalizing flow
Author: Sergey Samsonov
Author-email: svsamsonov@hse.ru
Maintainer: Evgeny Lagutin
Maintainer-email: lagutin.em@phystech.edu
Requires-Python: >=3.8
Classifier: License :: OSI Approved :: MIT License
Classifier: Programming Language :: Python :: 3
Classifier: Programming Language :: Python :: 3.8
Classifier: Programming Language :: Python :: 3.9
Classifier: Programming Language :: Python :: 3.10
Classifier: Programming Language :: Python :: 3.11
Requires-Dist: easydict
Requires-Dist: gdown
Requires-Dist: jax (>=0.4.8,<0.5.0)
Requires-Dist: jaxlib (>=0.4.7,<0.5.0)
Requires-Dist: pot (>=0.9.0,<0.10.0)
Requires-Dist: pyro-ppl (>=1.8.4,<2.0.0)
Requires-Dist: ruamel.yaml
Requires-Dist: seaborn (>=0.12.2,<0.13.0)
Requires-Dist: torch (>=2.0.0,<3.0.0)
Requires-Dist: torchvision
Project-URL: Documentation, http://github.com/svsamsonov/ex2mcmc_new/blob/master/README.md
Project-URL: Repository, http://github.com/svsamsonov/ex2mcmc_new.git
